mainentry/__init__.py
mainentry/mainentry.py
mainentry/py.typed
mainentry-2.0.dist-info/LICENSE
mainentry-2.0.dist-info/WHEEL
mainentry-2.0.dist-info/METADATA
mainentry-2.0.dist-info/RECORD
