Metadata-Version: 2.1
Name: mainentry
Version: 2.0
Summary: Wrapper to replace if __name__ == "__main__": with a decorator
Home-page: https://github.com/fanoway/main-entry
Author: fanoway
Requires-Python: >=2.6
Classifier: License :: OSI Approved :: MIT License
